common_utils/__init__.py
common_utils/logger.py
common_utils/tracing.py
observavility_completed-0.3.1.dist-info/METADATA
observavility_completed-0.3.1.dist-info/WHEEL
observavility_completed-0.3.1.dist-info/top_level.txt
observavility_completed-0.3.1.dist-info/RECORD
