Metadata-Version: 2.4
Name: observavility-completed
Version: 0.3.1
Summary: Librería compartida de logger y tracing para microservicios con async
Author-email: daniveloper <elmerhackxcrack@gmail.com>
License: MIT
Requires-Python: >=3.9
Requires-Dist: structlog<26.0.0,>=23.0.0
Requires-Dist: opentelemetry-distro
Requires-Dist: opentelemetry-exporter-otlp
Requires-Dist: opentelemetry-instrumentation-fastapi
Requires-Dist: opentelemetry-instrumentation-sqlalchemy
Requires-Dist: opentelemetry-instrumentation-requests
Requires-Dist: opentelemetry-instrumentation-httpx
